chronosys/Chronosys.py
chronosys/ChronosysDecoder.py
chronosys/ChronosysEncoder.py
chronosys/IndexedStorage.py
chronosys/__init__.py
Chronosys-0.1.0.dist-info/LICENSE
Chronosys-0.1.0.dist-info/METADATA
Chronosys-0.1.0.dist-info/WHEEL
Chronosys-0.1.0.dist-info/top_level.txt
Chronosys-0.1.0.dist-info/RECORD
