Metadata-Version: 2.2
Name: Chronosys
Version: 0.1.0
Summary: A Python library for creating and managing JSON files for information storage and retrieval.
Author-email: Jacob Allen <jacob@shredbox.com>
Keywords: json,storage
Classifier: Intended Audience :: Developers
Classifier: License :: OSI Approved :: GNU General Public License v3 (GPLv3)
Classifier: Programming Language :: Python :: 3
Classifier: Programming Language :: Python :: 3.8
Classifier: Programming Language :: Python :: 3.9
Classifier: Programming Language :: Python :: 3.10
Classifier: Programming Language :: Python :: 3.11
Classifier: Topic :: Software Development :: Libraries :: Python Modules
Requires-Python: >=3.8
License-File: LICENSE
